MANIFEST.in
README.md
setup.cfg
setup.py
laceworkjupyter/__init__.py
laceworkjupyter/accessors.py
laceworkjupyter/config.py
laceworkjupyter/decorators.py
laceworkjupyter/helper.py
laceworkjupyter/manager.py
laceworkjupyter/utils.py
laceworkjupyter/version.py
laceworkjupyter.egg-info/PKG-INFO
laceworkjupyter.egg-info/SOURCES.txt
laceworkjupyter.egg-info/dependency_links.txt
laceworkjupyter.egg-info/requires.txt
laceworkjupyter.egg-info/top_level.txt
laceworkjupyter/features/__init__.py
laceworkjupyter/features/client.py
laceworkjupyter/features/date.py
laceworkjupyter/features/filters.yaml
laceworkjupyter/features/hunt.py
laceworkjupyter/features/policies.py
laceworkjupyter/features/query.py
laceworkjupyter/features/query.yaml
laceworkjupyter/features/tables.yaml
laceworkjupyter/features/utils.py
laceworkjupyter/plugins/__init__.py
laceworkjupyter/plugins/alert_rules.py
laceworkjupyter/plugins/datasources.py