Metadata-Version: 2.1
Name: laceworkjupyter
Version: 0.1.2
Summary: Community-developed Jupyter helper for the Lacework Python SDK
Home-page: https://github.com/lacework/python-sdk
Author: Kristinn Gudjonsson
Author-email: kristinn.gudjonsson@lacework.net
License: MIT
Download-URL: https://pypi.python.org/pypi/laceworkjupyter
Keywords: lacework,api,sdk,python,api,jupyter,notebook
Platform: UNKNOWN
Classifier: Development Status :: 4 - Beta
Classifier: Intended Audience :: Developers
Classifier: Topic :: Software Development :: Build Tools
Classifier: License :: OSI Approved :: MIT License
Classifier: Programming Language :: Python :: 3
Classifier: Programming Language :: Python :: 3.6
Classifier: Programming Language :: Python :: 3.7
Classifier: Programming Language :: Python :: 3.8
Classifier: Programming Language :: Python :: 3.9
